llm_metadata_harvester/__init__.py
llm_metadata_harvester/cheatsheet.py
llm_metadata_harvester/checks.py
llm_metadata_harvester/checks_demo.py
llm_metadata_harvester/checks_repeat_demo.py
llm_metadata_harvester/harvester_operations.py
llm_metadata_harvester/llm_client.py
llm_metadata_harvester/prompt.py
llm_metadata_harvester/standards.py
llm_metadata_harvester/utils.py
llm_metadata_harvester/webutils.py
llm_metadata_harvester-0.1.3.dist-info/licenses/LICENSE
llm_metadata_harvester-0.1.3.dist-info/METADATA
llm_metadata_harvester-0.1.3.dist-info/WHEEL
llm_metadata_harvester-0.1.3.dist-info/top_level.txt
llm_metadata_harvester-0.1.3.dist-info/RECORD
